pymtodo/__init__.py
pymtodo/connect.py
pymtodo/list.py
pymtodo/task.py
pymtodo-0.2.dist-info/METADATA
pymtodo-0.2.dist-info/RECORD
pymtodo-0.2.dist-info/WHEEL
pymtodo-0.2.dist-info/top_level.txt
