Metadata-Version: 2.1
Name: pymtodo
Version: 0.2
Summary: Unofficial Microsoft To-Do python library
Home-page: https://github.com/efiminem/pymtodo
Author: Efim Mazhnik
Author-email: efimmazhnik@gmail.com
License: UNKNOWN
Download-URL: https://github.com/efiminem/pymtodo/archive/v0.2.zip
Platform: UNKNOWN
Classifier: Development Status :: 2 - Pre-Alpha
Classifier: License :: OSI Approved :: MIT License
Classifier: Programming Language :: Python :: 3
Classifier: Operating System :: OS Independent
